akshay_helloworld.py
akshay_helloworld-0.0.2.dist-info/LICENSE.txt
akshay_helloworld-0.0.2.dist-info/METADATA
akshay_helloworld-0.0.2.dist-info/WHEEL
akshay_helloworld-0.0.2.dist-info/top_level.txt
akshay_helloworld-0.0.2.dist-info/RECORD
